sphinx_sizzle_theme/__init__.py
sphinx_sizzle_theme/genindex.html
sphinx_sizzle_theme/layout.html
sphinx_sizzle_theme/logo-text.html
sphinx_sizzle_theme/search.html
sphinx_sizzle_theme/theme.conf
sphinx_sizzle_theme/version.txt
sphinx_sizzle_theme/static/css/sizzle.css
sphinx_sizzle_theme-0.1.3.dist-info/LICENSE
sphinx_sizzle_theme-0.1.3.dist-info/METADATA
sphinx_sizzle_theme-0.1.3.dist-info/WHEEL
sphinx_sizzle_theme-0.1.3.dist-info/entry_points.txt
sphinx_sizzle_theme-0.1.3.dist-info/top_level.txt
sphinx_sizzle_theme-0.1.3.dist-info/RECORD
