Metadata-Version: 2.1
Name: sphinx-sizzle-theme
Version: 0.1.3
Summary: The Sizzle theme for Sphinx.
Home-page: https://docs.red-dove.com/sphinx_sizzle_theme/
Author: Vinay Sajip
Author-email: vinay_sajip@yahoo.co.uk
Maintainer: Vinay Sajip
Maintainer-email: vinay_sajip@yahoo.co.uk
License: MIT
Project-URL: Documentation, https://docs.red-dove.com/sphinx_sizzle_theme/
Project-URL: Source, https://github.com/vsajip/sphinx_sizzle_theme
Project-URL: Tracker, https://github.com/vsajip/sphinx_sizzle_theme/issues
Keywords: documentation,sphinx,theme
Platform: any
Classifier: Framework :: Sphinx
Classifier: Framework :: Sphinx :: Theme
Classifier: Development Status :: 5 - Production/Stable
Classifier: License :: OSI Approved :: MIT License
Classifier: Environment :: Console
Classifier: Environment :: Web Environment
Classifier: Intended Audience :: Developers
Classifier: Programming Language :: Python
Classifier: Programming Language :: Python :: Implementation
Classifier: Programming Language :: Python :: 2.7
Classifier: Programming Language :: Python :: 3
Classifier: Programming Language :: Python :: 3.6
Classifier: Programming Language :: Python :: 3.7
Classifier: Programming Language :: Python :: 3.8
Classifier: Programming Language :: Python :: 3.9
Classifier: Programming Language :: Python :: 3.10
Classifier: Programming Language :: Python :: 3.11
Classifier: Operating System :: OS Independent
Classifier: Topic :: Documentation
License-File: LICENSE
Requires-Dist: sphinx
